repo_digest/__init__.py
repo_digest/cli.py
repo_digest/core.py
repo_digest-0.1.0.dist-info/METADATA
repo_digest-0.1.0.dist-info/WHEEL
repo_digest-0.1.0.dist-info/entry_points.txt
repo_digest-0.1.0.dist-info/licenses/LICENSE
repo_digest-0.1.0.dist-info/RECORD
