Metadata-Version: 2.4
Name: repo-digest
Version: 0.1.0
Summary: Turn any repository into an AI-ready text bundle with safe defaults and rich analytics.
Author: Your Name
License: MIT
License-File: LICENSE
Keywords: ai,analysis,export,llm,repository,text,tiktoken,tokens
Classifier: Environment :: Console
Classifier: License :: OSI Approved :: MIT License
Classifier: Operating System :: OS Independent
Classifier: Programming Language :: Python :: 3
Classifier: Topic :: Software Development :: Build Tools
Classifier: Topic :: Utilities
Requires-Python: >=3.8
Provides-Extra: dev
Requires-Dist: pytest>=7.0.0; extra == 'dev'
Provides-Extra: tiktoken
Requires-Dist: tiktoken>=0.4.0; extra == 'tiktoken'
